MANIFEST.in
README
README.md
requirements.txt
setup.cfg
setup.py
aws_spot_fleet_helper.egg-info/PKG-INFO
aws_spot_fleet_helper.egg-info/SOURCES.txt
aws_spot_fleet_helper.egg-info/dependency_links.txt
aws_spot_fleet_helper.egg-info/requires.txt
aws_spot_fleet_helper.egg-info/top_level.txt
mcmweb/__init__.py
mcmweb/aws_spot_fleet_helper/__init__.py
mcmweb/aws_spot_fleet_helper/spot_fleet_config.py
mcmweb/aws_spot_fleet_helper/spot_fleet_tagger.py
test/__init__.py
test/spot_fleet_config_test.py