Metadata-Version: 1.1
Name: aws-spot-fleet-helper
Version: 0.2.0
Summary: Python library to help launching a fleet of Spot instances within AWS infrastructure
Home-page: https://gitlab.com/equake/aws_spot_fleet_helper-spot-fleet-helper/
Author: Marcos Araujo Sobrinho
Author-email: marcos@mcmweb.com.br
License: MIT
Download-URL: https://pypi.python.org/pypi/aws-spot-fleet-helper
Keywords: aws,boto3,spot-fleet,spot,fleet,amazon web services
Platform: UNKNOWN
